osm/__init__.py
osm/parser.py
osm/road.py
osmRoad-0.2.dist-info/LICENSE
osmRoad-0.2.dist-info/METADATA
osmRoad-0.2.dist-info/WHEEL
osmRoad-0.2.dist-info/top_level.txt
osmRoad-0.2.dist-info/RECORD
