Metadata-Version: 2.1
Name: osmRoad
Version: 0.2
Summary: Parse OSM Data
Home-page: https://github.com/ChenZhongPu/osmRoad
Author: Zhongpu Chen
Author-email: chenloveit@gmail.com
License: UNKNOWN
Platform: UNKNOWN
Classifier: Programming Language :: Python :: 3
Classifier: License :: OSI Approved :: MIT License
Classifier: Operating System :: OS Independent
